esgmetrics/__init__.py
esgmetrics/esgscraper/__init__.py
esgmetrics/esgscraper/__main__.py
esgmetrics/esgscraper/csrhub.py
esgmetrics/esgscraper/msci.py
esgmetrics/esgscraper/scraper.py
esgmetrics/esgscraper/snp_global.py
esgmetrics/esgscraper/sustainanalytics.py
esgmetrics/esgscraper/yahoo.py
esgmetrics/esgscraper/data/Forbes.csv
esgmetrics/rds_uploader/__init__.py
esgmetrics/rds_uploader/rds_module.py
ESGScraper-1.0.0.dist-info/LICENSE
ESGScraper-1.0.0.dist-info/METADATA
ESGScraper-1.0.0.dist-info/WHEEL
ESGScraper-1.0.0.dist-info/top_level.txt
ESGScraper-1.0.0.dist-info/RECORD
