Metadata-Version: 2.1
Name: ESGScraper
Version: 1.0.0
Summary: Package that allows you to find ESG ratings from Yahoo    Finance, MSCI, CSR Hub, S&P Global, SustainAnalytics. In addition,    financial information is also scraped from Yahoo Finance
Home-page: https://github.com/shweta-29/Companies_ESG_Scraper.git
Author: Shweta Yadav
Author-email: shweta.yadav2092@gmail.com
License: MIT
Download-URL: https://github.com/shweta-29/Companies_ESG_Scraper/archive/refs/tags/v_01.tar.gz
Platform: UNKNOWN
License-File: LICENSE
Requires-Dist: selenium
Requires-Dist: pandas
Requires-Dist: tqdm
Requires-Dist: sqlalchemy
